haas/__init__.py
haas/__main__.py
haas/_version.py
haas/error_holder.py
haas/exceptions.py
haas/haas_application.py
haas/loader.py
haas/main.py
haas/module_import_error.py
haas/plugin_context.py
haas/plugin_manager.py
haas/result.py
haas/suite.py
haas/testing.py
haas/utils.py
haas/plugins/__init__.py
haas/plugins/base_hook_plugin.py
haas/plugins/coverage.py
haas/plugins/discoverer.py
haas/plugins/i_discoverer_plugin.py
haas/plugins/i_hook_plugin.py
haas/plugins/i_result_handler_plugin.py
haas/plugins/i_runner_plugin.py
haas/plugins/parallel_runner.py
haas/plugins/result_handler.py
haas/plugins/runner.py
haas/plugins/tests/__init__.py
haas/plugins/tests/test_coverage.py
haas/plugins/tests/test_discoverer.py
haas/plugins/tests/test_result_handlers.py
haas/tests/__init__.py
haas/tests/_test_case_data.py
haas/tests/_test_cases.py
haas/tests/builder.py
haas/tests/compat.py
haas/tests/fixtures.py
haas/tests/test_buffering.py
haas/tests/test_builder.py
haas/tests/test_deprecations.py
haas/tests/test_error_holder.py
haas/tests/test_fail_test.py
haas/tests/test_haas_application.py
haas/tests/test_loader.py
haas/tests/test_parallel_runner.py
haas/tests/test_plugin_context.py
haas/tests/test_plugin_manager.py
haas/tests/test_quiet_result_handler.py
haas/tests/test_runner.py
haas/tests/test_standard_result_handler.py
haas/tests/test_suite.py
haas/tests/test_test_duration_ordering.py
haas/tests/test_text_test_result.py
haas/tests/test_utils.py
haas/tests/test_verbose_result_handler.py
haas-0.9.0.dist-info/LICENSE.txt
haas-0.9.0.dist-info/METADATA
haas-0.9.0.dist-info/WHEEL
haas-0.9.0.dist-info/entry_points.txt
haas-0.9.0.dist-info/top_level.txt
haas-0.9.0.dist-info/RECORD
